pyapptest/__init__.py
pyapptest/cli.py
pyapptest/manager.py
pyapptest-1.0.0.dist-info/licenses/LICENSE
pyapptest-1.0.0.dist-info/METADATA
pyapptest-1.0.0.dist-info/WHEEL
pyapptest-1.0.0.dist-info/entry_points.txt
pyapptest-1.0.0.dist-info/top_level.txt
pyapptest-1.0.0.dist-info/RECORD
