Metadata-Version: 2.4
Name: pyapptest
Version: 1.0.0
Summary: Manager for fastapptest and flaskapptest libraries
Author-email: Ganesh Nalawade <your_email@example.com>
License-Expression: MIT
Requires-Python: >=3.10
License-File: LICENSE
Requires-Dist: fastapptest>=1.0.0
Requires-Dist: flaskapptest>=1.0.0
Dynamic: license-file
